[
  {
    "Type": "InternalMethodCarDataAsset",
    "Name": "DA_BP_LA400KCuTD",
    "Class": "UScriptClass'InternalMethodCarDataAsset'",
    "Flags": "RF_Public | RF_Standalone | RF_WasLoaded | RF_LoadCompleted",
    "Properties": {
      "CarData": {
        "ID": 154,
        "CarId": "CAR154",
        "CarNameId": "TRANCE DRIVE",
        "ModelNameId": "LA400KCuTD",
        "FolderId": "LA400KCuTD",
        "ReleaseDay": 2015,
        "Price": 1873800,
        "BodyType": "EBodyType::CONVERTIBLE_CAR",
        "FWeight": 510,
        "RWeight": 340,
        "Weight": 850,
        "Length": 3395,
        "Height": 1280,
        "Width": 1475,
        "GroundCearance": 110,
        "Wheelbase": 2230,
        "FTread": 1310,
        "RTread": 1295,
        "CenterOfGravity": 317.81,
        "DriveType": "EDriveType::DT_FF",
        "EngineKind": "EEngineKind::Straight4",
        "EngineFromat": "EEngineFromat::E_SR20DET",
        "EngineInspiration": "ECarIceAspirationType::Turbo",
        "Displacement": 1998,
        "MaxPower": 205,
        "MaxPowerRpm": 6000,
        "MaxTorque": 28.0,
        "MaxTorqueRpm": 4000,
        "FTireWidth": 225,
        "FTireOblateness": 30,
        "FTireInch": 17,
        "RTireWidth": 225,
        "RTireOblateness": 30,
        "RTireInch": 17,
        "GearNum": 5,
        "Gear1": 3.321,
        "Gear2": 1.902,
        "Gear3": 1.308,
        "Gear4": 1.0,
        "Gear5": 0.759,
        "GearFinal": 4.083,
        "BackGear": 3.382,
        "FSuspension": "EFSuspension::STRUT",
        "RSuspension": "ERSuspension::TORSION_BEAM",
        "Cd": 0.3,
        "Cl": 0.008,
        "RearDriveRate": 0.0,
        "EngineFormatName": "SR20DET",
        "front_damper_coef": 0.0,
        "rear_damper_coef": 0.0,
        "front_tire_grip": 1.45,
        "rear_tire_grip": 1.45,
        "front_tire_side_grip": 0.76,
        "rear_tire_side_grip": 0.84,
        "front_brake_angle": 200.0,
        "rear_brake_angle": 340.0,
        "FTireInchMinus": -2,
        "FTireInchPlus": 2,
        "RTireInchMinus": -2,
        "RTireInchPlus": 2,
        "CarName": {
          "TableId": "/Game/ITSB/UI/StringTable/ST_carname.ST_carname",
          "Key": "LA400KCuTD",
          "SourceString": "TRANCE DRIVE",
          "LocalizedString": "TRANCE DRIVE"
        },
        "FrontHightOffset": -30,
        "RearHightOffset": -30,
        "FrontCamberAngle": -20,
        "RearCamberAngle": -30,
        "FrontOffset": 70,
        "RearOffset": 80,
        "FrontTirePulling": 30,
        "RearTirePulling": 30,
        "MaxHightOffset": 2.5,
        "MinTurningRadius": 4.6,
        "FrontTireWidthMax": 245,
        "RearTireWidthMax": 245
      }
    }
  }
]