[
  {
    "Type": "InternalMethodEngineDataAsset",
    "Name": "DA_PU_OtTRUCK",
    "Class": "UScriptClass'InternalMethodEngineDataAsset'",
    "Flags": "RF_Public | RF_Standalone | RF_WasLoaded | RF_LoadCompleted",
    "Properties": {
      "EngineData": {
        "CarId": "CAR120",
        "CarNameId": "Dyna (XZU402) '99",
        "FolderId": "OtTRUCK",
        "EngineKind": "EEngineKind::Straight4",
        "EngineFormatName": "15B-FTE",
        "LevelData": [
          {
            "Key": "0",
            "Value": {
              "Level": 0,
              "RevLimit": 5500,
              "RedZoon": 5000,
              "Displacement": 4104,
              "MaxRpm": 7000,
              "MaxPower_ps": 170,
              "MaxPowerRpm": 3000,
              "MaxTorque_kg_m": 43.0,
              "MaxTorqueRpm": 1600,
              "MaxBoostNum": 0.0,
              "TachoMeter": 1,
              "BoostMeter": 0,
              "IsTurbo": false,
              "Weight": 0,
              "RpmData": [
                30.0,
                35.0,
                40.0,
                43.0,
                42.2,
                41.6,
                41.0,
                40.6,
                33.698,
                27.97,
                23.21,
                19.27,
                15.99
              ],
              "MaxTorqueCoef": 0.9,
              "VTECrpm": 0
            }
          },
          {
            "Key": "1",
            "Value": {
              "Level": 1,
              "RevLimit": 5500,
              "RedZoon": 5000,
              "Displacement": 4104,
              "MaxRpm": 7000,
              "MaxPower_ps": 190,
              "MaxPowerRpm": 3200,
              "MaxTorque_kg_m": 43.9,
              "MaxTorqueRpm": 2000,
              "MaxBoostNum": 0.0,
              "TachoMeter": 1,
              "BoostMeter": 0,
              "IsTurbo": false,
              "Weight": 0,
              "RpmData": [
                30.6,
                35.7,
                40.8,
                43.86,
                43.9,
                43.28,
                42.66,
                42.24,
                35.06,
                29.1,
                23.67,
                19.66,
                16.31
              ],
              "MaxTorqueCoef": 0.9,
              "VTECrpm": 0
            }
          },
          {
            "Key": "2",
            "Value": {
              "Level": 2,
              "RevLimit": 5500,
              "RedZoon": 5000,
              "Displacement": 4104,
              "MaxRpm": 7000,
              "MaxPower_ps": 201,
              "MaxPowerRpm": 3200,
              "MaxTorque_kg_m": 46.53,
              "MaxTorqueRpm": 2000,
              "MaxBoostNum": 0.0,
              "TachoMeter": 1,
              "BoostMeter": 0,
              "IsTurbo": false,
              "Weight": 0,
              "RpmData": [
                32.44,
                37.84,
                43.25,
                46.49,
                46.53,
                45.88,
                45.22,
                44.77,
                37.16,
                30.85,
                25.09,
                20.84,
                17.29
              ],
              "MaxTorqueCoef": 0.9,
              "VTECrpm": 0
            }
          },
          {
            "Key": "3",
            "Value": {
              "Level": 3,
              "RevLimit": 5500,
              "RedZoon": 5000,
              "Displacement": 4309,
              "MaxRpm": 7000,
              "MaxPower_ps": 217,
              "MaxPowerRpm": 3200,
              "MaxTorque_kg_m": 50.29,
              "MaxTorqueRpm": 2000,
              "MaxBoostNum": 0.0,
              "TachoMeter": 1,
              "BoostMeter": 0,
              "IsTurbo": false,
              "Weight": 0,
              "RpmData": [
                35.05,
                40.9,
                46.74,
                50.24,
                50.29,
                49.58,
                48.87,
                48.39,
                40.16,
                33.34,
                27.11,
                22.52,
                18.68
              ],
              "MaxTorqueCoef": 0.9,
              "VTECrpm": 0
            }
          },
          {
            "Key": "4",
            "Value": {
              "Level": 4,
              "RevLimit": 5500,
              "RedZoon": 5000,
              "Displacement": 4309,
              "MaxRpm": 7000,
              "MaxPower_ps": 228,
              "MaxPowerRpm": 3200,
              "MaxTorque_kg_m": 52.8,
              "MaxTorqueRpm": 2000,
              "MaxBoostNum": 0.0,
              "TachoMeter": 1,
              "BoostMeter": 0,
              "IsTurbo": false,
              "Weight": 0,
              "RpmData": [
                36.8,
                42.94,
                49.08,
                52.75,
                52.8,
                52.06,
                51.31,
                50.81,
                42.17,
                35.01,
                29.89,
                24.83,
                20.59
              ],
              "MaxTorqueCoef": 0.9,
              "VTECrpm": 0
            }
          },
          {
            "Key": "5",
            "Value": {
              "Level": 5,
              "RevLimit": 5500,
              "RedZoon": 5000,
              "Displacement": 4309,
              "MaxRpm": 7000,
              "MaxPower_ps": 266,
              "MaxPowerRpm": 3200,
              "MaxTorque_kg_m": 61.58,
              "MaxTorqueRpm": 2000,
              "MaxBoostNum": 0.587891,
              "TachoMeter": 1,
              "BoostMeter": 1,
              "IsTurbo": true,
              "Weight": 0,
              "RpmData": [
                39.74,
                46.38,
                53.01,
                56.97,
                61.58,
                60.72,
                59.84,
                59.26,
                49.18,
                40.83,
                32.28,
                26.82,
                22.24
              ],
              "MaxTorqueCoef": 0.9,
              "VTECrpm": 0
            }
          },
          {
            "Key": "6",
            "Value": {
              "Level": 6,
              "RevLimit": 5500,
              "RedZoon": 5000,
              "Displacement": 4514,
              "MaxRpm": 7000,
              "MaxPower_ps": 287,
              "MaxPowerRpm": 3200,
              "MaxTorque_kg_m": 66.51,
              "MaxTorqueRpm": 2000,
              "MaxBoostNum": 0.637129,
              "TachoMeter": 1,
              "BoostMeter": 1,
              "IsTurbo": true,
              "Weight": 0,
              "RpmData": [
                42.92,
                50.09,
                57.25,
                61.53,
                66.51,
                65.58,
                64.63,
                64.0,
                53.11,
                44.1,
                34.86,
                28.97,
                24.02
              ],
              "MaxTorqueCoef": 0.9,
              "VTECrpm": 0
            }
          },
          {
            "Key": "7",
            "Value": {
              "Level": 7,
              "RevLimit": 6000,
              "RedZoon": 5500,
              "Displacement": 4514,
              "MaxRpm": 7500,
              "MaxPower_ps": 316,
              "MaxPowerRpm": 3200,
              "MaxTorque_kg_m": 73.16,
              "MaxTorqueRpm": 2000,
              "MaxBoostNum": 0.800817,
              "TachoMeter": 1,
              "BoostMeter": 1,
              "IsTurbo": true,
              "Weight": 0,
              "RpmData": [
                47.21,
                55.1,
                62.98,
                67.68,
                73.16,
                72.14,
                71.09,
                70.4,
                58.42,
                48.51,
                38.35,
                31.87,
                26.42,
                21.14
              ],
              "MaxTorqueCoef": 0.9,
              "VTECrpm": 0
            }
          },
          {
            "Key": "8",
            "Value": {
              "Level": 8,
              "RevLimit": 6500,
              "RedZoon": 6000,
              "Displacement": 4514,
              "MaxRpm": 8000,
              "MaxPower_ps": 338,
              "MaxPowerRpm": 3200,
              "MaxTorque_kg_m": 78.28,
              "MaxTorqueRpm": 2000,
              "MaxBoostNum": 0.926845,
              "TachoMeter": 1,
              "BoostMeter": 1,
              "IsTurbo": true,
              "Weight": 0,
              "RpmData": [
                50.51,
                58.96,
                67.39,
                72.42,
                78.28,
                77.19,
                76.07,
                75.33,
                62.51,
                51.91,
                45.13,
                37.51,
                31.1,
                24.88,
                19.91,
                14.48
              ],
              "MaxTorqueCoef": 0.9,
              "VTECrpm": 0
            }
          },
          {
            "Key": "9",
            "Value": {
              "Level": 9,
              "RevLimit": 6500,
              "RedZoon": 6000,
              "Displacement": 4514,
              "MaxRpm": 8000,
              "MaxPower_ps": 359,
              "MaxPowerRpm": 3200,
              "MaxTorque_kg_m": 83.01,
              "MaxTorqueRpm": 2000,
              "MaxBoostNum": 1.043273,
              "TachoMeter": 1,
              "BoostMeter": 1,
              "IsTurbo": true,
              "Weight": 0,
              "RpmData": [
                53.57,
                62.53,
                71.46,
                76.8,
                83.01,
                81.86,
                80.67,
                79.88,
                66.3,
                55.05,
                47.86,
                39.78,
                32.98,
                26.39,
                21.12,
                15.35
              ],
              "MaxTorqueCoef": 0.9,
              "VTECrpm": 0
            }
          }
        ],
        "SoundId": 6
      }
    }
  }
]