[
  {
    "Type": "InternalMethodEngineDataAsset",
    "Name": "DA_PU_GRX133",
    "Class": "UScriptClass'InternalMethodEngineDataAsset'",
    "Flags": "RF_Public | RF_Standalone | RF_WasLoaded | RF_LoadCompleted",
    "Properties": {
      "EngineData": {
        "CarId": "CAR134",
        "CarNameId": "MARK X 350RDS (GRX133) '16",
        "FolderId": "GRX133",
        "EngineKind": "EEngineKind::V6",
        "EngineFormatName": "2GR-FSE",
        "LevelData": [
          {
            "Key": "0",
            "Value": {
              "Level": 0,
              "RevLimit": 6600,
              "RedZoon": 6600,
              "displacement": 3456,
              "MaxRpm": 8000,
              "MaxPower_ps": 318,
              "MaxPowerRpm": 6400,
              "MaxTorque_kg_m": 38.7,
              "MaxTorqueRpm": 4800,
              "MaxBoostNum": 0.0,
              "TachoMeter": 1,
              "BoostMeter": 0,
              "IsTurbo": false,
              "Weight": 0,
              "RpmData": [
                25.0,
                25.0,
                25.0,
                33.0,
                36.0,
                35.9,
                35.8,
                35.6,
                36.4,
                37.8,
                38.4,
                38.7,
                38.0,
                37.4,
                36.4,
                35.75
              ],
              "MaxTorqueCoef": 0.8
            }
          },
          {
            "Key": "1",
            "Value": {
              "Level": 1,
              "RevLimit": 6600,
              "RedZoon": 6600,
              "displacement": 3456,
              "MaxRpm": 8000,
              "MaxPower_ps": 322,
              "MaxPowerRpm": 6400,
              "MaxTorque_kg_m": 38.76,
              "MaxTorqueRpm": 4800,
              "MaxBoostNum": 0.0,
              "TachoMeter": 1,
              "BoostMeter": 0,
              "IsTurbo": false,
              "Weight": 0,
              "RpmData": [
                25.04,
                25.04,
                25.04,
                33.05,
                36.23,
                36.13,
                36.03,
                35.82,
                36.63,
                38.04,
                37.89,
                38.76,
                38.06,
                37.46,
                36.46,
                35.81
              ],
              "MaxTorqueCoef": 0.8
            }
          },
          {
            "Key": "2",
            "Value": {
              "Level": 2,
              "RevLimit": 6600,
              "RedZoon": 6600,
              "displacement": 3456,
              "MaxRpm": 8000,
              "MaxPower_ps": 332,
              "MaxPowerRpm": 6400,
              "MaxTorque_kg_m": 39.24,
              "MaxTorqueRpm": 4800,
              "MaxBoostNum": 0.0,
              "TachoMeter": 1,
              "BoostMeter": 0,
              "IsTurbo": false,
              "Weight": 0,
              "RpmData": [
                25.35,
                25.35,
                25.35,
                33.45,
                36.67,
                36.58,
                36.47,
                36.26,
                37.08,
                38.51,
                38.35,
                39.24,
                38.52,
                37.92,
                35.8,
                36.93
              ],
              "MaxTorqueCoef": 0.8
            }
          },
          {
            "Key": "3",
            "Value": {
              "Level": 3,
              "RevLimit": 6600,
              "RedZoon": 6600,
              "displacement": 3628,
              "MaxRpm": 8000,
              "MaxPower_ps": 333,
              "MaxPowerRpm": 6400,
              "MaxTorque_kg_m": 39.43,
              "MaxTorqueRpm": 4800,
              "MaxBoostNum": 0.0,
              "TachoMeter": 1,
              "BoostMeter": 0,
              "IsTurbo": false,
              "Weight": 0,
              "RpmData": [
                25.47,
                25.47,
                25.47,
                33.61,
                36.86,
                36.77,
                36.65,
                36.44,
                37.27,
                38.71,
                38.54,
                39.43,
                38.72,
                38.11,
                35.98,
                37.12
              ],
              "MaxTorqueCoef": 0.8
            }
          },
          {
            "Key": "4",
            "Value": {
              "Level": 4,
              "RevLimit": 6600,
              "RedZoon": 6600,
              "displacement": 3628,
              "MaxRpm": 8000,
              "MaxPower_ps": 343,
              "MaxPowerRpm": 6400,
              "MaxTorque_kg_m": 42.6,
              "MaxTorqueRpm": 4800,
              "MaxBoostNum": 0.0,
              "TachoMeter": 1,
              "BoostMeter": 0,
              "IsTurbo": false,
              "Weight": 0,
              "RpmData": [
                26.21,
                26.21,
                26.21,
                34.58,
                37.93,
                37.84,
                37.71,
                37.49,
                38.35,
                39.84,
                41.64,
                42.6,
                41.84,
                41.18,
                38.88,
                38.2
              ],
              "MaxTorqueCoef": 0.8
            }
          },
          {
            "Key": "5",
            "Value": {
              "Level": 5,
              "RevLimit": 6600,
              "RedZoon": 6600,
              "displacement": 3628,
              "MaxRpm": 8000,
              "MaxPower_ps": 371,
              "MaxPowerRpm": 6400,
              "MaxTorque_kg_m": 46.47,
              "MaxTorqueRpm": 4000,
              "MaxBoostNum": 0.42319,
              "TachoMeter": 1,
              "BoostMeter": 1,
              "IsTurbo": true,
              "Weight": 0,
              "RpmData": [
                28.31,
                28.31,
                28.31,
                37.35,
                44.24,
                44.14,
                43.99,
                43.73,
                44.73,
                46.47,
                44.97,
                46.01,
                45.19,
                44.47,
                41.99,
                41.26
              ],
              "MaxTorqueCoef": 0.8
            }
          },
          {
            "Key": "6",
            "Value": {
              "Level": 6,
              "RevLimit": 6600,
              "RedZoon": 6600,
              "displacement": 3801,
              "MaxRpm": 8000,
              "MaxPower_ps": 400,
              "MaxPowerRpm": 6400,
              "MaxTorque_kg_m": 50.19,
              "MaxTorqueRpm": 4000,
              "MaxBoostNum": 0.467158,
              "TachoMeter": 1,
              "BoostMeter": 1,
              "IsTurbo": true,
              "Weight": 0,
              "RpmData": [
                30.57,
                30.57,
                30.57,
                40.34,
                47.78,
                47.67,
                47.51,
                47.23,
                48.31,
                50.19,
                48.57,
                49.69,
                48.81,
                48.03,
                45.35,
                44.56
              ],
              "MaxTorqueCoef": 0.8
            }
          },
          {
            "Key": "7",
            "Value": {
              "Level": 7,
              "RevLimit": 6600,
              "RedZoon": 6600,
              "displacement": 3801,
              "MaxRpm": 8000,
              "MaxPower_ps": 433,
              "MaxPowerRpm": 6400,
              "MaxTorque_kg_m": 51.7,
              "MaxTorqueRpm": 4000,
              "MaxBoostNum": 0.511298,
              "TachoMeter": 1,
              "BoostMeter": 1,
              "IsTurbo": true,
              "Weight": 0,
              "RpmData": [
                31.49,
                31.49,
                31.49,
                41.55,
                49.21,
                49.1,
                48.94,
                48.65,
                49.76,
                51.7,
                50.03,
                51.18,
                50.27,
                49.47,
                46.71,
                48.2
              ],
              "MaxTorqueCoef": 0.8
            }
          },
          {
            "Key": "8",
            "Value": {
              "Level": 8,
              "RevLimit": 6600,
              "RedZoon": 6600,
              "displacement": 3801,
              "MaxRpm": 8000,
              "MaxPower_ps": 437,
              "MaxPowerRpm": 6400,
              "MaxTorque_kg_m": 56.77,
              "MaxTorqueRpm": 4800,
              "MaxBoostNum": 0.659505,
              "TachoMeter": 1,
              "BoostMeter": 1,
              "IsTurbo": true,
              "Weight": 0,
              "RpmData": [
                32.4,
                32.4,
                32.4,
                42.76,
                50.64,
                50.53,
                50.36,
                50.06,
                51.2,
                53.19,
                55.49,
                56.77,
                55.76,
                54.87,
                51.82,
                48.61
              ],
              "MaxTorqueCoef": 0.8
            }
          },
          {
            "Key": "9",
            "Value": {
              "Level": 9,
              "RevLimit": 6600,
              "RedZoon": 6600,
              "displacement": 3801,
              "MaxRpm": 8000,
              "MaxPower_ps": 485,
              "MaxPowerRpm": 6400,
              "MaxTorque_kg_m": 63.07,
              "MaxTorqueRpm": 4800,
              "MaxBoostNum": 0.843667,
              "TachoMeter": 1,
              "BoostMeter": 1,
              "IsTurbo": true,
              "Weight": 0,
              "RpmData": [
                35.99,
                35.99,
                35.99,
                47.51,
                56.26,
                56.14,
                55.95,
                55.62,
                56.88,
                59.09,
                61.64,
                63.07,
                61.95,
                60.96,
                57.57,
                54.01
              ],
              "MaxTorqueCoef": 0.8
            }
          }
        ],
        "SoundId": 6
      }
    }
  }
]